{"metadata":{"host":"main","model":{"packagePath":"/Users/zqlu/Sources/eclipse-theia/theia-dev-kit/plugins/vscode.emmet/extension","packageUri":"file:///Users/zqlu/Sources/eclipse-theia/theia-dev-kit/plugins/vscode.emmet/extension","id":"vscode.emmet","name":"emmet","publisher":"vscode","version":"1.88.1","displayName":"Emmet (built-in)","description":"Emmet support for VS Code","engine":{"type":"vscode","version":"^1.13.0"},"entryPoint":{"backend":"/Users/zqlu/Sources/eclipse-theia/theia-dev-kit/plugins/vscode.emmet/extension/dist/node/emmetNodeMain"},"iconUrl":"hostedPlugin/vscode_emmet/images%2Ficon.png","readmeUrl":"hostedPlugin/vscode_emmet/.%2FREADME.md","licenseUrl":"hostedPlugin/vscode_emmet/.%2FLICENSE"},"lifecycle":{"startMethod":"activate","stopMethod":"deactivate","frontendModuleName":"vscode_emmet","frontendInitPath":"plugin-vscode-init-fe.js","backendInitPath":"/Users/zqlu/Sources/eclipse-theia/theia-dev-kit/browser-app/lib/backend/plugin-vscode-init"},"outOfSync":false,"isUnderDevelopment":false},"type":0,"contributes":{"activationEvents":["onCommand:emmet.expandAbbreviation","onLanguage","onCommand:editor.emmet.action.wrapWithAbbreviation","onCommand:editor.emmet.action.removeTag","onCommand:editor.emmet.action.updateTag","onCommand:editor.emmet.action.matchTag","onCommand:editor.emmet.action.balanceIn","onCommand:editor.emmet.action.balanceOut","onCommand:editor.emmet.action.prevEditPoint","onCommand:editor.emmet.action.nextEditPoint","onCommand:editor.emmet.action.mergeLines","onCommand:editor.emmet.action.selectPrevItem","onCommand:editor.emmet.action.selectNextItem","onCommand:editor.emmet.action.splitJoinTag","onCommand:editor.emmet.action.toggleComment","onCommand:editor.emmet.action.evaluateMathExpression","onCommand:editor.emmet.action.updateImageSize","onCommand:editor.emmet.action.incrementNumberByOneTenth","onCommand:editor.emmet.action.incrementNumberByOne","onCommand:editor.emmet.action.incrementNumberByTen","onCommand:editor.emmet.action.decrementNumberByOneTenth","onCommand:editor.emmet.action.decrementNumberByOne","onCommand:editor.emmet.action.decrementNumberByTen","onCommand:editor.emmet.action.reflectCSSValue","onCommand:workbench.action.showEmmetCommands"],"configuration":[{"type":"object","title":"Emmet","properties":{"emmet.showExpandedAbbreviation":{"type":["string"],"enum":["never","always","inMarkupAndStylesheetFilesOnly"],"default":"always","markdownDescription":"%emmetShowExpandedAbbreviation%","owner":"Emmet"},"emmet.showAbbreviationSuggestions":{"type":"boolean","default":true,"scope":"language-overridable","markdownDescription":"%emmetShowAbbreviationSuggestions%","owner":"Emmet"},"emmet.includeLanguages":{"type":"object","additionalProperties":{"type":"string"},"default":{},"markdownDescription":"%emmetIncludeLanguages%","owner":"Emmet"},"emmet.variables":{"type":"object","properties":{"lang":{"type":"string","default":"en"},"charset":{"type":"string","default":"UTF-8"}},"additionalProperties":{"type":"string"},"default":{},"markdownDescription":"%emmetVariables%","owner":"Emmet"},"emmet.syntaxProfiles":{"type":"object","default":{},"markdownDescription":"%emmetSyntaxProfiles%","owner":"Emmet"},"emmet.excludeLanguages":{"type":"array","items":{"type":"string"},"default":["markdown"],"markdownDescription":"%emmetExclude%","owner":"Emmet"},"emmet.extensionsPath":{"type":"array","items":{"type":"string","markdownDescription":"%emmetExtensionsPathItem%"},"default":[],"scope":"machine-overridable","markdownDescription":"%emmetExtensionsPath%","owner":"Emmet"},"emmet.triggerExpansionOnTab":{"type":"boolean","default":false,"scope":"language-overridable","markdownDescription":"%emmetTriggerExpansionOnTab%","owner":"Emmet"},"emmet.useInlineCompletions":{"type":"boolean","default":false,"markdownDescription":"%emmetUseInlineCompletions%","owner":"Emmet"},"emmet.preferences":{"type":"object","default":{},"markdownDescription":"%emmetPreferences%","properties":{"css.intUnit":{"type":"string","default":"px","markdownDescription":"%emmetPreferencesIntUnit%"},"css.floatUnit":{"type":"string","default":"em","markdownDescription":"%emmetPreferencesFloatUnit%"},"css.propertyEnd":{"type":"string","default":";","markdownDescription":"%emmetPreferencesCssAfter%"},"sass.propertyEnd":{"type":"string","default":"","markdownDescription":"%emmetPreferencesSassAfter%"},"stylus.propertyEnd":{"type":"string","default":"","markdownDescription":"%emmetPreferencesStylusAfter%"},"css.valueSeparator":{"type":"string","default":": ","markdownDescription":"%emmetPreferencesCssBetween%"},"sass.valueSeparator":{"type":"string","default":": ","markdownDescription":"%emmetPreferencesSassBetween%"},"stylus.valueSeparator":{"type":"string","default":" ","markdownDescription":"%emmetPreferencesStylusBetween%"},"bem.elementSeparator":{"type":"string","default":"__","markdownDescription":"%emmetPreferencesBemElementSeparator%"},"bem.modifierSeparator":{"type":"string","default":"_","markdownDescription":"%emmetPreferencesBemModifierSeparator%"},"filter.commentBefore":{"type":"string","default":"","markdownDescription":"%emmetPreferencesFilterCommentBefore%"},"filter.commentAfter":{"type":"string","default":"\n<!-- /[#ID][.CLASS] -->","markdownDescription":"%emmetPreferencesFilterCommentAfter%"},"filter.commentTrigger":{"type":"array","default":["id","class"],"markdownDescription":"%emmetPreferencesFilterCommentTrigger%"},"format.noIndentTags":{"type":"array","default":["html"],"markdownDescription":"%emmetPreferencesFormatNoIndentTags%"},"format.forceIndentationForTags":{"type":"array","default":["body"],"markdownDescription":"%emmetPreferencesFormatForceIndentTags%"},"profile.allowCompactBoolean":{"type":"boolean","default":false,"markdownDescription":"%emmetPreferencesAllowCompactBoolean%"},"css.webkitProperties":{"type":"string","default":null,"markdownDescription":"%emmetPreferencesCssWebkitProperties%"},"css.mozProperties":{"type":"string","default":null,"markdownDescription":"%emmetPreferencesCssMozProperties%"},"css.oProperties":{"type":"string","default":null,"markdownDescription":"%emmetPreferencesCssOProperties%"},"css.msProperties":{"type":"string","default":null,"markdownDescription":"%emmetPreferencesCssMsProperties%"},"css.fuzzySearchMinScore":{"type":"number","default":0.3,"markdownDescription":"%emmetPreferencesCssFuzzySearchMinScore%"},"output.inlineBreak":{"type":"number","default":0,"markdownDescription":"%emmetPreferencesOutputInlineBreak%"},"output.reverseAttributes":{"type":"boolean","default":false,"markdownDescription":"%emmetPreferencesOutputReverseAttributes%"},"output.selfClosingStyle":{"type":"string","enum":["html","xhtml","xml"],"default":"html","markdownDescription":"%emmetPreferencesOutputSelfClosingStyle%"},"css.color.short":{"type":"boolean","default":true,"markdownDescription":"%emmetPreferencesCssColorShort%"}},"owner":"Emmet"},"emmet.showSuggestionsAsSnippets":{"type":"boolean","default":false,"markdownDescription":"%emmetShowSuggestionsAsSnippets%","owner":"Emmet"},"emmet.optimizeStylesheetParsing":{"type":"boolean","default":true,"markdownDescription":"%emmetOptimizeStylesheetParsing%","owner":"Emmet"}}}],"commands":[{"command":"editor.emmet.action.wrapWithAbbreviation","title":"%command.wrapWithAbbreviation%","category":"Emmet"},{"command":"editor.emmet.action.removeTag","title":"%command.removeTag%","category":"Emmet"},{"command":"editor.emmet.action.updateTag","title":"%command.updateTag%","category":"Emmet"},{"command":"editor.emmet.action.matchTag","title":"%command.matchTag%","category":"Emmet"},{"command":"editor.emmet.action.balanceIn","title":"%command.balanceIn%","category":"Emmet"},{"command":"editor.emmet.action.balanceOut","title":"%command.balanceOut%","category":"Emmet"},{"command":"editor.emmet.action.prevEditPoint","title":"%command.prevEditPoint%","category":"Emmet"},{"command":"editor.emmet.action.nextEditPoint","title":"%command.nextEditPoint%","category":"Emmet"},{"command":"editor.emmet.action.mergeLines","title":"%command.mergeLines%","category":"Emmet"},{"command":"editor.emmet.action.selectPrevItem","title":"%command.selectPrevItem%","category":"Emmet"},{"command":"editor.emmet.action.selectNextItem","title":"%command.selectNextItem%","category":"Emmet"},{"command":"editor.emmet.action.splitJoinTag","title":"%command.splitJoinTag%","category":"Emmet"},{"command":"editor.emmet.action.toggleComment","title":"%command.toggleComment%","category":"Emmet"},{"command":"editor.emmet.action.evaluateMathExpression","title":"%command.evaluateMathExpression%","category":"Emmet"},{"command":"editor.emmet.action.updateImageSize","title":"%command.updateImageSize%","category":"Emmet"},{"command":"editor.emmet.action.incrementNumberByOneTenth","title":"%command.incrementNumberByOneTenth%","category":"Emmet"},{"command":"editor.emmet.action.incrementNumberByOne","title":"%command.incrementNumberByOne%","category":"Emmet"},{"command":"editor.emmet.action.incrementNumberByTen","title":"%command.incrementNumberByTen%","category":"Emmet"},{"command":"editor.emmet.action.decrementNumberByOneTenth","title":"%command.decrementNumberByOneTenth%","category":"Emmet"},{"command":"editor.emmet.action.decrementNumberByOne","title":"%command.decrementNumberByOne%","category":"Emmet"},{"command":"editor.emmet.action.decrementNumberByTen","title":"%command.decrementNumberByTen%","category":"Emmet"},{"command":"editor.emmet.action.reflectCSSValue","title":"%command.reflectCSSValue%","category":"Emmet"},{"command":"workbench.action.showEmmetCommands","title":"%command.showEmmetCommands%","category":""}],"menus":{"commandPalette":[{"command":"editor.emmet.action.wrapWithAbbreviation","when":"!activeEditorIsReadonly"},{"command":"editor.emmet.action.removeTag","when":"!activeEditorIsReadonly"},{"command":"editor.emmet.action.updateTag","when":"!activeEditorIsReadonly"},{"command":"editor.emmet.action.matchTag","when":"!activeEditorIsReadonly"},{"command":"editor.emmet.action.balanceIn","when":"!activeEditorIsReadonly"},{"command":"editor.emmet.action.balanceOut","when":"!activeEditorIsReadonly"},{"command":"editor.emmet.action.prevEditPoint","when":"!activeEditorIsReadonly"},{"command":"editor.emmet.action.nextEditPoint","when":"!activeEditorIsReadonly"},{"command":"editor.emmet.action.mergeLines","when":"!activeEditorIsReadonly"},{"command":"editor.emmet.action.selectPrevItem","when":"!activeEditorIsReadonly"},{"command":"editor.emmet.action.selectNextItem","when":"!activeEditorIsReadonly"},{"command":"editor.emmet.action.splitJoinTag","when":"!activeEditorIsReadonly"},{"command":"editor.emmet.action.toggleComment","when":"!activeEditorIsReadonly"},{"command":"editor.emmet.action.evaluateMathExpression","when":"!activeEditorIsReadonly"},{"command":"editor.emmet.action.updateImageSize","when":"!activeEditorIsReadonly"},{"command":"editor.emmet.action.incrementNumberByOneTenth","when":"!activeEditorIsReadonly"},{"command":"editor.emmet.action.incrementNumberByOne","when":"!activeEditorIsReadonly"},{"command":"editor.emmet.action.incrementNumberByTen","when":"!activeEditorIsReadonly"},{"command":"editor.emmet.action.decrementNumberByOneTenth","when":"!activeEditorIsReadonly"},{"command":"editor.emmet.action.decrementNumberByOne","when":"!activeEditorIsReadonly"},{"command":"editor.emmet.action.decrementNumberByTen","when":"!activeEditorIsReadonly"},{"command":"editor.emmet.action.reflectCSSValue","when":"!activeEditorIsReadonly"}]}}}
